{
    "error": false,
    "donate_url": "https://paypal.me/ChaitanayaMittal",
    "website_url": "https://revengeos.com/",
    "news_url": "https://t.me/RevengeOSNews",
    "datetime": 1590056077.7087007,
    "filename": "RevengeOS-3.2-Q-OFFICIAL-X00T-20200520-1851.zip",
    "id": "",
    "size": "624215229",
    "url": "https://osdn.net/frs/redir.php?f=%2Fstorage%2Fg%2Fr%2Fre%2Frevengeos%2FX00T%2FRevengeOS-3.2-Q-OFFICIAL-X00T-20200520-1851.zip",
    "version": "3.2",
    "filehash": "83d592e6fe28e83bac8241a9abce2a28"
}